repo_context/__init__.py
repo_context/cli.py
repo_context/converter.py
repo_context/ignore.py
repo_context/structure.py
repo_context/utils.py
repo_context/webpage.py
repo_context-0.4.0.dist-info/METADATA
repo_context-0.4.0.dist-info/WHEEL
repo_context-0.4.0.dist-info/entry_points.txt
repo_context-0.4.0.dist-info/licenses/LICENSE
repo_context-0.4.0.dist-info/RECORD
