Metadata-Version: 2.4
Name: repo-context
Version: 0.4.0
Summary: Convert Git repositories into LLM-friendly context format
Author-email: Mathias Nielsen <mathiasesn1@gmail.com>
Maintainer-email: Mathias Nielsen <mathiasesn1@gmail.com>
License: MIT License
License-File: LICENSE
Requires-Python: >=3.10
Requires-Dist: gitpython>=3.1.43
Requires-Dist: markdownify>=0.14.1
Requires-Dist: python-dotenv>=1.0.1
Requires-Dist: requests>=2.32.3
Requires-Dist: rich>=13.9.4
Requires-Dist: tqdm>=4.67.1
